[{"id": 33, "title": "Banana Bread", "price": "0.50", "imagepath": "documents/images/Banana-Bread.gif", "alt": "A package of crackers", "active": true}, {"id": 35, "title": "Bottled Water", "price": "0.50", "imagepath": "documents/images/bottledwater.gif", "alt": "16 ounce bottle of water", "active": true}, {"id": 38, "title": "Chips", "price": "0.50", "imagepath": "documents/images/chips.gif", "alt": "10 oz bag of chips", "active": true}, {"id": 60, "title": "Chocolate Doughnut", "price": "4.25", "imagepath": "y", "alt": "Yummy ball of chocolaty dough", "active": true}, {"id": 39, "title": "Cinnamon Roll", "price": "1.00", "imagepath": "documents/images/Cinnamon-Rolls.gif", "alt": "A cinnamon roll", "active": true}, {"id": 40, "title": "Cookies", "price": "0.50", "imagepath": "documents/images/cookie.gif", "alt": "A big yummy cookie", "active": true}, {"id": 12, "title": "Frappuccino", "price": "1.00", "imagepath": "documents/images/frap_77AOwYJ.gif", "alt": "12 ounce bottle of Frappuccino", "active": true}, {"id": 61, "title": "French Fries", "price": "3.25", "imagepath": "y", "alt": "Hot Potatoes", "active": true}, {"id": 13, "title": "Gatorade", "price": "1.00", "imagepath": "documents/images/gatorade_iPAbtXy.gif", "alt": "16 ounce bottle of Gatorade", "active": true}, {"id": 20, "title": "Laffy Taffy (3)", "price": "0.25", "imagepath": "documents/images/laffy-taffy.gif", "alt": "12 ounce bottle of Apple Juice", "active": true}, {"id": 45, "title": "Monster Energy", "price": "2.00", "imagepath": "documents/images/monster-energy.gif", "alt": "16 ounce can of Monster Energy drink", "active": true}, {"id": 46, "title": "Monster Energy x2", "price": "3.50", "imagepath": "documents/images/monster-energy2.gif", "alt": "16 ounce cans of Monster Energy drink", "active": true}, {"id": 47, "title": "Peanuts", "price": "0.75", "imagepath": "documents/images/peanuts.gif", "alt": "A package of peanuts", "active": true}, {"id": 48, "title": "Pickle", "price": "1.00", "imagepath": "documents/images/dill-pickle.gif", "alt": "A Pickle", "active": true}, {"id": 49, "title": "Rice Krispy Treat", "price": "0.50", "imagepath": "documents/images/ricetreat.gif", "alt": "A Rice Krispy Treat", "active": true}, {"id": 50, "title": "Soda", "price": "0.50", "imagepath": "documents/images/soda.gif", "alt": "12 oz can of Soda", "active": true}, {"id": 51, "title": "Tea", "price": "1.00", "imagepath": "documents/images/tea.gif", "alt": "16 ounce bottle of tea", "active": true}, {"id": 18, "title": "Vitamin Water", "price": "1.00", "imagepath": "documents/images/vitamin-water.gif", "alt": "16 ounce bottle of Vitamin Water", "active": true}]